{
  "coins": [
    "AAVE",
    "ADA",
    "APT",
    "ARB",
    "AVAX",
    "BNB",
    "BONK",
    "BTC",
    "CAKE",
    "CFX",
    "CRV",
    "DOGE",
    "DOT",
    "ENA",
    "ETH",
    "FET",
    "FIL",
    "FLOKI",
    "HBAR",
    "ICP",
    "LINK",
    "LTC",
    "NEAR",
    "PAXG",
    "PENDLE",
    "PEPE",
    "SEI",
    "SHIB",
    "SOL",
    "SUI",
    "TAO",
    "TRX",
    "UNI",
    "WIF",
    "WLD",
    "XLM",
    "XRP",
    "ZEC",
    "ZEN"
  ],
  "quality_window": {
    "start": "2024-10-01",
    "end": "2025-03-15"
  },
  "rebalance_hours": 2,
  "quality_leaderboard": [
    {
      "detector": "hmm_market",
      "quality_score": -0.089613,
      "transitions": 14,
      "counts": "{\"1\": 535, \"0\": 70, \"2\": 22}",
      "regime_stats": "{\"0\": {\"count\": 54, \"fwd_24h_mean\": -0.040926, \"fwd_72h_mean\": -0.096409, \"fwd_24h_pos_rate\": 0.3148, \"fwd_72h_pos_rate\": 0.0, \"future_vol_24h\": 0.011767}, \"1\": {\"count\": 492, \"fwd_24h_mean\": 0.022776, \"fwd_72h_mean\": 0.058306, \"fwd_24h_pos_rate\": 0.5955, \"fwd_72h_pos_rate\": 0.6138, \"future_vol_24h\": 0.012643}, \"2\": {\"count\": 9, \"fwd_24h_mean\": -0.010348, \"fwd_72h_mean\": -0.008156, \"fwd_24h_pos_rate\": 0.3333, \"fwd_72h_pos_rate\": 0.3333, \"future_vol_24h\": 0.010407}}"
    }
  ],
  "backtests": []
}